LICENSE
MANIFEST.in
README.rst
requirements.txt
setup.py
test-requirements.txt
simdeplower/__init__.py
simdeplower/executable.py
simdeplower/ovfhelper.py
simdeplower/simconfigs.py
simdeplower/simprov.py
simdeplower/vmrunhelper.py
simdeplower.egg-info/PKG-INFO
simdeplower.egg-info/SOURCES.txt
simdeplower.egg-info/dependency_links.txt
simdeplower.egg-info/entry_points.txt
simdeplower.egg-info/requires.txt
simdeplower.egg-info/top_level.txt
simdeplower.egg-info/zip-safe