Metadata-Version: 1.1
Name: simdeplower
Version: 0.1
Summary: Tool to deploy VCSA to Fusion or Workstation and configure Simulator
Home-page: https://github.com/virtdevninja/simdeplower.git
Author: Michael Rice
Author-email: michael@michaelrice.org
License: License :: OSI Approved :: Apache Software License
Platform: Windows
Platform: Linux
Platform: Solaris
Platform: Mac OS-X
Platform: Unix
Classifier: Development Status :: 5 - Production/Stable
Classifier: License :: OSI Approved :: Apache Software License
Classifier: Intended Audience :: Information Technology
Classifier: Intended Audience :: System Administrators
Classifier: Intended Audience :: Developers
Classifier: Environment :: Console
Classifier: Programming Language :: Python :: 2
Classifier: Programming Language :: Python :: 2.7
Classifier: Topic :: Software Development :: Libraries :: Python Modules
Classifier: Topic :: System :: Distributed Computing
Classifier: Operating System :: Microsoft :: Windows
Classifier: Operating System :: POSIX
Classifier: Operating System :: Unix
Classifier: Operating System :: MacOS
